itkspec/ReadSpec.py
itkspec/__init__.py
itkspec/__main__.py
itkspec-1.5.3.dist-info/METADATA
itkspec-1.5.3.dist-info/WHEEL
itkspec-1.5.3.dist-info/entry_points.txt
itkspec-1.5.3.dist-info/top_level.txt
itkspec-1.5.3.dist-info/RECORD
