Metadata-Version: 2.4
Name: itkspec
Version: 1.5.3
Summary: A python package responsible for retrieving component specifications from a unified database. This tool can also operate as an API since it is built with the FastAPI framework.
Author-email: Eduardo Daemon <edudaemonsantos@gmail.com>, Pedro Glaser de Senna <glaserdesennapedro@gmail.com>
Project-URL: Homepage, https://gitlab.cern.ch/atlas-itk-production-software/common-interfaces/itk-pdb-specifica.git
Keywords: itk,cern,specifications,itkdb
Classifier: Programming Language :: Python
Classifier: Programming Language :: Python :: 3
Requires-Dist: feedparser>=5.2.0
Requires-Dist: html2text
Requires-Dist: tomli; python_version < "3.11"
Requires-Dist: pandas
Requires-Dist: fastapi
Requires-Dist: pyjwt
Requires-Dist: itkdb
Requires-Dist: requests
Requires-Dist: fastapi.responses
Requires-Dist: fastapi.security
Requires-Dist: datetime
Requires-Dist: uvicorn
Requires-Dist: jinja2
Requires-Dist: python-multipart
Requires-Dist: pytest
Requires-Dist: tabulate
Provides-Extra: dev
Requires-Dist: black; extra == "dev"
Requires-Dist: bumpver; extra == "dev"
Requires-Dist: isort; extra == "dev"
Requires-Dist: pip-tools; extra == "dev"
Requires-Dist: pytest; extra == "dev"
